tmuxer/__init__.py
tmuxer/main.py
tmuxer/shmw
tmuxer/shmw.c
tmuxer-0.1.4.dist-info/licenses/LICENSE
tmuxer-0.1.4.dist-info/METADATA
tmuxer-0.1.4.dist-info/WHEEL
tmuxer-0.1.4.dist-info/top_level.txt
tmuxer-0.1.4.dist-info/RECORD
