Metadata-Version: 2.4
Name: tmuxer
Version: 0.1.4
Summary: Run commands in tmux sessions
Author-email: Dinesh <dinesh883248@gmail.com>
License: MIT
Requires-Python: >=3.7
License-File: LICENSE
Dynamic: license-file
